agentnet/__init__.py
agentnet/agentnet.py
agentnet-0.1.data/data/LICENSE.txt
agentnet-0.1.dist-info/LICENSE.txt
agentnet-0.1.dist-info/METADATA
agentnet-0.1.dist-info/WHEEL
agentnet-0.1.dist-info/top_level.txt
agentnet-0.1.dist-info/RECORD
